pypasscrypt/__init__.py
pypasscrypt/connectionhandler.py
pypasscrypt/cryptohandler.py
pypasscrypt/passwordhandler.py
pypasscrypt/storagehandler.py
pypasscrypt/userinterface.py
pypasscrypt-2.0.1.dist-info/entry_points.txt
pypasscrypt-2.0.1.dist-info/license
pypasscrypt-2.0.1.dist-info/METADATA
pypasscrypt-2.0.1.dist-info/WHEEL
pypasscrypt-2.0.1.dist-info/RECORD
