Metadata-Version: 2.1
Name: pypasscrypt
Version: 2.0.1
Summary: a module for testing new python features
License: None
Author: tejus3131
Author-email: tejus3131@gmail.com
Requires-Python: >=3.11,<4.0
Classifier: License :: Other/Proprietary License
Classifier: Programming Language :: Python :: 3
Classifier: Programming Language :: Python :: 3.11
Classifier: Programming Language :: Python :: 3.12
Requires-Dist: click (>=8.1.7,<9.0.0)
Requires-Dist: cryptography (>=42.0.8,<43.0.0)
Requires-Dist: inquirerpy (>=0.3.4,<0.4.0)
Requires-Dist: pydantic (>=2.8.2,<3.0.0)
Requires-Dist: pyperclip (>=1.9.0,<2.0.0)
Requires-Dist: rich (>=13.7.1,<14.0.0)
Requires-Dist: tqdm (>=4.66.4,<5.0.0)
